{
  "<": 1360,
  "!": 46,
  "d": 717,
  "o": 1613,
  "c": 1086,
  "t": 2612,
  "y": 432,
  "p": 953,
  "e": 3148,
  " ": 11829,
  "h": 815,
  "m": 809,
  "l": 1717,
  ">": 1425,
  "\n": 1080,
  "-": 903,
  "[": 28,
  "i": 1983,
  "f": 443,
  "I": 52,
  "E": 57,
  "7": 40,
  "]": 28,
  "a": 2034,
  "s": 2041,
  "=": 1088,
  "\"": 2144,
  "n": 1608,
  "j": 90,
  "6": 44,
  "8": 44,
  "9": 31,
  "g": 441,
  "r": 1643,
  "G": 32,
  "(": 40,
  ".": 318,
  ")": 40,
  ":": 152,
  "/": 1428,
  "w": 279,
  "?": 8,
  "T": 47,
  "F": 38,
  "3": 121,
  "5": 45,
  "Y": 4,
  "C": 48,
  "V": 9,
  "H": 15,
  "L": 40,
  "|": 8,
  ";": 56,
  "u": 650,
  "{": 6,
  "}": 6,
  "'": 62,
  ",": 77,
  "D": 38,
  "q": 43,
  "v": 286,
  "X": 2,
  "U": 19,
  "A": 48,
  "b": 248,
  "k": 120,
  "x": 74,
  "1": 153,
  "2": 268,
  "P": 159,
  "0": 205,
  "4": 78,
  "K": 4,
  "B": 35,
  "z": 18,
  "J": 11,
  "W": 17,
  "M": 28,
  "N": 35,
  "R": 13,
  "S": 101,
  "O": 13,
  "Z": 1,
  "+": 19,
  "&": 39,
  "#": 37,
  "_": 23,
  "@": 3,
  "Q": 9,
  "\r": 73,
  "*": 4,
  "\\": 3,
  "\u2019": 1,
  "%": 1
}
